kiara/__init__.py
kiara/api.py
kiara/defaults.py
kiara/exceptions.py
kiara/py.typed
kiara/version.txt
kiara/context/__init__.py
kiara/context/config.py
kiara/context/orm.py
kiara/context/runtime_config.py
kiara/data_types/__init__.py
kiara/data_types/included_core_types/__init__.py
kiara/data_types/included_core_types/filesystem.py
kiara/data_types/included_core_types/metadata.py
kiara/data_types/included_core_types/serialization.py
kiara/data_types/included_core_types/internal/__init__.py
kiara/data_types/included_core_types/internal/render_value.py
kiara/doc/__init__.py
kiara/doc/gen_info_pages.py
kiara/doc/generate_api_doc.py
kiara/doc/mkdocs_macros_cli.py
kiara/doc/mkdocs_macros_kiara.py
kiara/doc/mkdocstrings/__init__.py
kiara/doc/mkdocstrings/collector.py
kiara/doc/mkdocstrings/handler.py
kiara/doc/mkdocstrings/renderer.py
kiara/interfaces/__init__.py
kiara/interfaces/cli/__init__.py
kiara/interfaces/cli/proxy_cli.py
kiara/interfaces/cli/run.py
kiara/interfaces/cli/archive/__init__.py
kiara/interfaces/cli/archive/commands.py
kiara/interfaces/cli/context/__init__.py
kiara/interfaces/cli/context/commands.py
kiara/interfaces/cli/data/__init__.py
kiara/interfaces/cli/data/commands.py
kiara/interfaces/cli/info/__init__.py
kiara/interfaces/cli/info/commands.py
kiara/interfaces/cli/module/__init__.py
kiara/interfaces/cli/module/commands.py
kiara/interfaces/cli/operation/__init__.py
kiara/interfaces/cli/operation/commands.py
kiara/interfaces/cli/pipeline/__init__.py
kiara/interfaces/cli/pipeline/commands.py
kiara/interfaces/cli/plugin/__init__.py
kiara/interfaces/cli/plugin/commands.py
kiara/interfaces/cli/render/__init__.py
kiara/interfaces/cli/render/commands.py
kiara/interfaces/cli/type/__init__.py
kiara/interfaces/cli/type/commands.py
kiara/interfaces/cli/workflow/__init__.py
kiara/interfaces/cli/workflow/commands.py
kiara/interfaces/python_api/__init__.py
kiara/interfaces/python_api/base_api.py
kiara/interfaces/python_api/batch.py
kiara-0.5.18.dist-info/METADATA
kiara-0.5.18.dist-info/WHEEL
kiara-0.5.18.dist-info/entry_points.txt
kiara-0.5.18.dist-info/licenses/AUTHORS.rst
kiara-0.5.18.dist-info/licenses/LICENSE
kiara-0.5.18.dist-info/RECORD
